rss2sql/__init__.py
rss2sql/rss2sql.py
rss2sql-1.0.4.dist-info/LICENSE
rss2sql-1.0.4.dist-info/METADATA
rss2sql-1.0.4.dist-info/WHEEL
rss2sql-1.0.4.dist-info/entry_points.txt
rss2sql-1.0.4.dist-info/top_level.txt
rss2sql-1.0.4.dist-info/RECORD
