Metadata-Version: 2.1
Name: rss2sql
Version: 1.0.4
Summary: Convert RSS feed to SQL database
Home-page: https://github.com/jsjyhzy/rss2sql
Author: Hu Zheyang
Author-email: i@huzheyang.com
License: MIT
Platform: UNKNOWN
Classifier: Development Status :: 3 - Alpha
Classifier: Intended Audience :: End Users/Desktop
Classifier: License :: OSI Approved :: MIT License
Classifier: Programming Language :: Python :: 3 :: Only
Requires-Python: >=3
Requires-Dist: PyYAML (>=3.13)
Requires-Dist: requests (>=2.19.1)
Requires-Dist: SQLAlchemy (>=1.2.10)
Requires-Dist: feedparser (>=5.2.1)
